abci/__init__.py
abci/application.py
abci/server.py
abci/utils.py
example/__init__.py
example/counter.py
gogoproto/__init__.py
gogoproto/gogo_pb2.py
tendermint/__init__.py
tendermint/abci/__init__.py
tendermint/abci/types_pb2.py
tendermint/crypto/__init__.py
tendermint/crypto/keys_pb2.py
tendermint/crypto/proof_pb2.py
tendermint/types/__init__.py
tendermint/types/params_pb2.py
tendermint/types/types_pb2.py
tendermint/types/validator_pb2.py
tendermint/version/__init__.py
tendermint/version/types_pb2.py
abci-0.8.3.dist-info/LICENSE
abci-0.8.3.dist-info/METADATA
abci-0.8.3.dist-info/WHEEL
abci-0.8.3.dist-info/entry_points.txt
abci-0.8.3.dist-info/top_level.txt
abci-0.8.3.dist-info/RECORD
